acronymer/__init__.py
acronymer-0.0.4.dist-info/licenses/LICENSE
acronymer-0.0.4.dist-info/METADATA
acronymer-0.0.4.dist-info/WHEEL
acronymer-0.0.4.dist-info/top_level.txt
acronymer-0.0.4.dist-info/RECORD
