Metadata-Version: 2.4
Name: acronymer
Version: 0.0.4
Summary: Tools for getting creative with acronyms
Home-page: https://github.com/lyricalgrin/acronymer
License: mit
Platform: any
License-File: LICENSE
Requires-Dist: oa
Dynamic: license-file
